<?xml version="1.0" encoding="UTF-8"?><Global>
	<Char1>
		<name>大圆</name>
		<gender>女</gender>
		<career>战士</career>
		<level>49</level>
		<exp>1542700</exp>
		<dc>8-9</dc>
		<sc>0-0</sc>
		<mc>0-0</mc>
		<ac>6-7</ac>
		<mac>0-0</mac>
		<hp>974</hp>
		<mp>249</mp>
		<hit>17</hit>
		<dex>15</dex>
		<weapon>w26~裁决之杖+7  攻击: 0-37  重量: 80  持久: 32  需等级30</weapon>
		<upgradeCount>7</upgradeCount>
		<armor>c26~雷霆战甲(女)  防御: 5-12  魔御: 4-8  攻击: 1-3  重量: 60  持久: 60  需等级42</armor>
		<helmet>h4~道士头盔  防御: 1-4  魔御: 2-3  攻击: 0-3  道术: 0-1  魔法: 0-1  重量: 3  持久: 8  需等级24</helmet>
		<amulet>a24~圣战项链  攻击: 3-8  重量: 2  持久: 7  需攻击40</amulet>
		<medal>x3~三倍经验勋章  攻击: 3-3  道术: 3-3  魔法: 3-3  重量: 1  持久: 30  需等级1</medal>
		<leftBracelet>i28~雷霆护腕  防御: 0-2  魔御: 0-2  攻击: 1-4  重量: 1  持久: 7  需攻击45</leftBracelet>
		<rightBracelet>i28~雷霆护腕  防御: 0-2  魔御: 0-2  攻击: 1-4  重量: 1  持久: 8  需攻击45</rightBracelet>
		<leftRing>r28~雷霆战戒  攻击: 0-8  重量: 1  持久: 7  需攻击45</leftRing>
		<rightRing>r25~圣战戒指  魔御: 0-1  攻击: 0-7  魔法: 0-1  重量: 2  持久: 7  需攻击40</rightRing>
		<belt>b1~兽皮腰带  防御: 0-1  魔法: 0-1  重量: 1  持久: 6  需等级15</belt>
		<boots>o2~鹿皮靴  防御: 0-2  魔法: 0-2  重量: 1  持久: 8  需等级22</boots>
		<gem>g4~红宝石+3  防御: 4-4  魔御: 4-4  攻击: 4-4  道术: 4-4  魔法: 4-4  重量: 1  持久: 10  需等级45</gem>
		<money>20146803</money>
	</Char1>
	<WareHouse>
		<item>x2~双倍经验勋章  攻击: 2-2  道术: 2-2  魔法: 2-2  重量: 1  持久: 20  需等级1</item>
		<item>r35~传送戒指  攻击: 0-1  重量: 1  持久: 8  需等级12</item>
		<item/>
		<item/>
		<item/>
		<item/>
		<item/>
		<item/>
		<item/>
		<item/>
		<item/>
		<item/>
		<item/>
		<item/>
		<item/>
		<item/>
		<item/>
		<item/>
		<item/>
		<item/>
		<item/>
		<item/>
		<item/>
		<item/>
		<item/>
		<item/>
		<item/>
		<item/>
		<item/>
		<item/>
		<item/>
		<item/>
		<item/>
		<item/>
		<item/>
		<item/>
		<item/>
		<item/>
		<item/>
		<item/>
		<item/>
		<item/>
		<item/>
		<item/>
		<item/>
		<item/>
		<item/>
		<item/>
		<item/>
		<item/>
		<item/>
		<item/>
		<item/>
		<item/>
		<item/>
		<item/>
		<item/>
		<item/>
		<item/>
		<item/>
		<item/>
		<item/>
		<item/>
		<item/>
		<item/>
		<item/>
		<item/>
		<item/>
		<item/>
		<item/>
		<item/>
		<item/>
		<item/>
		<item/>
		<item/>
		<item/>
		<item/>
		<item/>
		<item/>
		<item/>
		<item/>
		<item/>
		<item/>
		<item/>
		<item/>
		<item/>
		<item/>
		<item/>
		<item/>
		<item/>
		<item/>
		<item/>
		<item/>
		<item/>
		<item/>
		<item/>
		<item/>
		<item/>
		<item/>
	</WareHouse>
	<Miscellanous>
		<ore1>56</ore1>
		<ore2>46</ore2>
		<charm1>16</charm1>
		<charm2>9</charm2>
		<charm3>1</charm3>
	</Miscellanous>
</Global>